[
  {
    "slug": "ancient-egypt",
    "name": "Ancient Egypt",
    "domain": "World History",
    "sort_order": 1
  },
  {
    "slug": "the-roman-empire",
    "name": "The Roman Empire",
    "domain": "World History",
    "sort_order": 2
  },
  {
    "slug": "ancient-greece",
    "name": "Ancient Greece",
    "domain": "World History",
    "sort_order": 3
  },
  {
    "slug": "medieval-europe",
    "name": "Medieval Europe",
    "domain": "World History",
    "sort_order": 4
  },
  {
    "slug": "the-renaissance",
    "name": "The Renaissance",
    "domain": "World History",
    "sort_order": 5
  },
  {
    "slug": "world-war-i",
    "name": "World War I",
    "domain": "World History",
    "sort_order": 6
  },
  {
    "slug": "world-war-ii",
    "name": "World War II",
    "domain": "World History",
    "sort_order": 7
  },
  {
    "slug": "the-cold-war",
    "name": "The Cold War",
    "domain": "World History",
    "sort_order": 8
  },
  {
    "slug": "ancient-china",
    "name": "Ancient China",
    "domain": "World History",
    "sort_order": 9
  },
  {
    "slug": "the-ottoman-empire",
    "name": "The Ottoman Empire",
    "domain": "World History",
    "sort_order": 10
  },
  {
    "slug": "the-french-revolution",
    "name": "The French Revolution",
    "domain": "World History",
    "sort_order": 11
  },
  {
    "slug": "the-american-revolution",
    "name": "The American Revolution",
    "domain": "World History",
    "sort_order": 12
  },
  {
    "slug": "the-industrial-revolution",
    "name": "The Industrial Revolution",
    "domain": "World History",
    "sort_order": 13
  },
  {
    "slug": "ancient-mesopotamia",
    "name": "Ancient Mesopotamia",
    "domain": "World History",
    "sort_order": 14
  },
  {
    "slug": "the-vikings",
    "name": "The Vikings",
    "domain": "World History",
    "sort_order": 15
  },
  {
    "slug": "the-british-empire",
    "name": "The British Empire",
    "domain": "World History",
    "sort_order": 16
  },
  {
    "slug": "feudal-japan",
    "name": "Feudal Japan",
    "domain": "World History",
    "sort_order": 17
  },
  {
    "slug": "the-mongol-empire",
    "name": "The Mongol Empire",
    "domain": "World History",
    "sort_order": 18
  },
  {
    "slug": "pre-columbian-americas",
    "name": "Pre-Columbian Americas",
    "domain": "World History",
    "sort_order": 19
  },
  {
    "slug": "the-age-of-exploration",
    "name": "The Age of Exploration",
    "domain": "World History",
    "sort_order": 20
  },
  {
    "slug": "classical-physics",
    "name": "Classical Physics",
    "domain": "Science & Nature",
    "sort_order": 21
  },
  {
    "slug": "quantum-mechanics",
    "name": "Quantum Mechanics",
    "domain": "Science & Nature",
    "sort_order": 22
  },
  {
    "slug": "the-periodic-table",
    "name": "The Periodic Table",
    "domain": "Science & Nature",
    "sort_order": 23
  },
  {
    "slug": "chemical-reactions",
    "name": "Chemical Reactions",
    "domain": "Science & Nature",
    "sort_order": 24
  },
  {
    "slug": "genetics-and-dna",
    "name": "Genetics & DNA",
    "domain": "Science & Nature",
    "sort_order": 25
  },
  {
    "slug": "evolution",
    "name": "Evolution",
    "domain": "Science & Nature",
    "sort_order": 26
  },
  {
    "slug": "cell-biology",
    "name": "Cell Biology",
    "domain": "Science & Nature",
    "sort_order": 27
  },
  {
    "slug": "thermodynamics",
    "name": "Thermodynamics",
    "domain": "Science & Nature",
    "sort_order": 28
  },
  {
    "slug": "electricity-and-magnetism",
    "name": "Electricity & Magnetism",
    "domain": "Science & Nature",
    "sort_order": 29
  },
  {
    "slug": "optics-and-light",
    "name": "Optics & Light",
    "domain": "Science & Nature",
    "sort_order": 30
  },
  {
    "slug": "nuclear-physics",
    "name": "Nuclear Physics",
    "domain": "Science & Nature",
    "sort_order": 31
  },
  {
    "slug": "organic-chemistry",
    "name": "Organic Chemistry",
    "domain": "Science & Nature",
    "sort_order": 32
  },
  {
    "slug": "ecology",
    "name": "Ecology",
    "domain": "Science & Nature",
    "sort_order": 33
  },
  {
    "slug": "photosynthesis",
    "name": "Photosynthesis",
    "domain": "Science & Nature",
    "sort_order": 34
  },
  {
    "slug": "the-scientific-method",
    "name": "The Scientific Method",
    "domain": "Science & Nature",
    "sort_order": 35
  },
  {
    "slug": "famous-scientists",
    "name": "Famous Scientists",
    "domain": "Science & Nature",
    "sort_order": 36
  },
  {
    "slug": "nobel-prize-discoveries",
    "name": "Nobel Prize Discoveries",
    "domain": "Science & Nature",
    "sort_order": 37
  },
  {
    "slug": "states-of-matter",
    "name": "States of Matter",
    "domain": "Science & Nature",
    "sort_order": 38
  },
  {
    "slug": "waves-and-sound",
    "name": "Waves & Sound",
    "domain": "Science & Nature",
    "sort_order": 39
  },
  {
    "slug": "forces-and-motion",
    "name": "Forces & Motion",
    "domain": "Science & Nature",
    "sort_order": 40
  },
  {
    "slug": "world-capitals",
    "name": "World Capitals",
    "domain": "Geography",
    "sort_order": 41
  },
  {
    "slug": "rivers-of-the-world",
    "name": "Rivers of the World",
    "domain": "Geography",
    "sort_order": 42
  },
  {
    "slug": "mountain-ranges",
    "name": "Mountain Ranges",
    "domain": "Geography",
    "sort_order": 43
  },
  {
    "slug": "oceans-and-seas",
    "name": "Oceans & Seas",
    "domain": "Geography",
    "sort_order": 44
  },
  {
    "slug": "deserts",
    "name": "Deserts",
    "domain": "Geography",
    "sort_order": 45
  },
  {
    "slug": "world-flags",
    "name": "World Flags",
    "domain": "Geography",
    "sort_order": 46
  },
  {
    "slug": "countries-of-africa",
    "name": "Countries of Africa",
    "domain": "Geography",
    "sort_order": 47
  },
  {
    "slug": "countries-of-asia",
    "name": "Countries of Asia",
    "domain": "Geography",
    "sort_order": 48
  },
  {
    "slug": "countries-of-europe",
    "name": "Countries of Europe",
    "domain": "Geography",
    "sort_order": 49
  },
  {
    "slug": "countries-of-the-americas",
    "name": "Countries of the Americas",
    "domain": "Geography",
    "sort_order": 50
  },
  {
    "slug": "islands-and-archipelagos",
    "name": "Islands & Archipelagos",
    "domain": "Geography",
    "sort_order": 51
  },
  {
    "slug": "volcanoes",
    "name": "Volcanoes",
    "domain": "Geography",
    "sort_order": 52
  },
  {
    "slug": "national-parks",
    "name": "National Parks",
    "domain": "Geography",
    "sort_order": 53
  },
  {
    "slug": "u-s-states",
    "name": "U.S. States",
    "domain": "Geography",
    "sort_order": 54
  },
  {
    "slug": "borders-and-boundaries",
    "name": "Borders & Boundaries",
    "domain": "Geography",
    "sort_order": 55
  },
  {
    "slug": "lakes-of-the-world",
    "name": "Lakes of the World",
    "domain": "Geography",
    "sort_order": 56
  },
  {
    "slug": "climate-zones",
    "name": "Climate Zones",
    "domain": "Geography",
    "sort_order": 57
  },
  {
    "slug": "time-zones",
    "name": "Time Zones",
    "domain": "Geography",
    "sort_order": 58
  },
  {
    "slug": "cartography-and-maps",
    "name": "Cartography & Maps",
    "domain": "Geography",
    "sort_order": 59
  },
  {
    "slug": "population-and-cities",
    "name": "Population & Cities",
    "domain": "Geography",
    "sort_order": 60
  },
  {
    "slug": "shakespeare",
    "name": "Shakespeare",
    "domain": "Literature",
    "sort_order": 61
  },
  {
    "slug": "greek-classics",
    "name": "Greek Classics",
    "domain": "Literature",
    "sort_order": 62
  },
  {
    "slug": "19th-century-novels",
    "name": "19th-Century Novels",
    "domain": "Literature",
    "sort_order": 63
  },
  {
    "slug": "modernist-literature",
    "name": "Modernist Literature",
    "domain": "Literature",
    "sort_order": 64
  },
  {
    "slug": "poetry",
    "name": "Poetry",
    "domain": "Literature",
    "sort_order": 65
  },
  {
    "slug": "science-fiction-books",
    "name": "Science Fiction Books",
    "domain": "Literature",
    "sort_order": 66
  },
  {
    "slug": "fantasy-literature",
    "name": "Fantasy Literature",
    "domain": "Literature",
    "sort_order": 67
  },
  {
    "slug": "detective-and-mystery-fiction",
    "name": "Detective & Mystery Fiction",
    "domain": "Literature",
    "sort_order": 68
  },
  {
    "slug": "nobel-laureates-in-literature",
    "name": "Nobel Laureates in Literature",
    "domain": "Literature",
    "sort_order": 69
  },
  {
    "slug": "children-s-literature",
    "name": "Children's Literature",
    "domain": "Literature",
    "sort_order": 70
  },
  {
    "slug": "russian-literature",
    "name": "Russian Literature",
    "domain": "Literature",
    "sort_order": 71
  },
  {
    "slug": "american-literature",
    "name": "American Literature",
    "domain": "Literature",
    "sort_order": 72
  },
  {
    "slug": "british-literature",
    "name": "British Literature",
    "domain": "Literature",
    "sort_order": 73
  },
  {
    "slug": "dystopian-fiction",
    "name": "Dystopian Fiction",
    "domain": "Literature",
    "sort_order": 74
  },
  {
    "slug": "epic-poetry",
    "name": "Epic Poetry",
    "domain": "Literature",
    "sort_order": 75
  },
  {
    "slug": "literary-characters",
    "name": "Literary Characters",
    "domain": "Literature",
    "sort_order": 76
  },
  {
    "slug": "opening-lines-and-passages",
    "name": "Opening Lines & Passages",
    "domain": "Literature",
    "sort_order": 77
  },
  {
    "slug": "banned-books",
    "name": "Banned Books",
    "domain": "Literature",
    "sort_order": 78
  },
  {
    "slug": "pulitzer-and-booker-winners",
    "name": "Pulitzer & Booker Winners",
    "domain": "Literature",
    "sort_order": 79
  },
  {
    "slug": "playwrights-and-drama",
    "name": "Playwrights & Drama",
    "domain": "Literature",
    "sort_order": 80
  },
  {
    "slug": "classic-hollywood",
    "name": "Classic Hollywood",
    "domain": "Film & Cinema",
    "sort_order": 81
  },
  {
    "slug": "oscar-best-pictures",
    "name": "Oscar Best Pictures",
    "domain": "Film & Cinema",
    "sort_order": 82
  },
  {
    "slug": "film-directors",
    "name": "Film Directors",
    "domain": "Film & Cinema",
    "sort_order": 83
  },
  {
    "slug": "film-noir",
    "name": "Film Noir",
    "domain": "Film & Cinema",
    "sort_order": 84
  },
  {
    "slug": "animated-films",
    "name": "Animated Films",
    "domain": "Film & Cinema",
    "sort_order": 85
  },
  {
    "slug": "science-fiction-films",
    "name": "Science Fiction Films",
    "domain": "Film & Cinema",
    "sort_order": 86
  },
  {
    "slug": "horror-films",
    "name": "Horror Films",
    "domain": "Film & Cinema",
    "sort_order": 87
  },
  {
    "slug": "movie-quotes",
    "name": "Movie Quotes",
    "domain": "Film & Cinema",
    "sort_order": 88
  },
  {
    "slug": "blockbuster-franchises",
    "name": "Blockbuster Franchises",
    "domain": "Film & Cinema",
    "sort_order": 89
  },
  {
    "slug": "foreign-language-films",
    "name": "Foreign Language Films",
    "domain": "Film & Cinema",
    "sort_order": 90
  },
  {
    "slug": "the-silent-film-era",
    "name": "The Silent Film Era",
    "domain": "Film & Cinema",
    "sort_order": 91
  },
  {
    "slug": "documentary-films",
    "name": "Documentary Films",
    "domain": "Film & Cinema",
    "sort_order": 92
  },
  {
    "slug": "movie-soundtracks",
    "name": "Movie Soundtracks",
    "domain": "Film & Cinema",
    "sort_order": 93
  },
  {
    "slug": "special-effects-and-vfx",
    "name": "Special Effects & VFX",
    "domain": "Film & Cinema",
    "sort_order": 94
  },
  {
    "slug": "cult-classics",
    "name": "Cult Classics",
    "domain": "Film & Cinema",
    "sort_order": 95
  },
  {
    "slug": "film-festivals",
    "name": "Film Festivals",
    "domain": "Film & Cinema",
    "sort_order": 96
  },
  {
    "slug": "actors-and-actresses",
    "name": "Actors & Actresses",
    "domain": "Film & Cinema",
    "sort_order": 97
  },
  {
    "slug": "superhero-movies",
    "name": "Superhero Movies",
    "domain": "Film & Cinema",
    "sort_order": 98
  },
  {
    "slug": "westerns",
    "name": "Westerns",
    "domain": "Film & Cinema",
    "sort_order": 99
  },
  {
    "slug": "movies-by-decade",
    "name": "Movies by Decade",
    "domain": "Film & Cinema",
    "sort_order": 100
  },
  {
    "slug": "classical-composers",
    "name": "Classical Composers",
    "domain": "Music",
    "sort_order": 101
  },
  {
    "slug": "the-beatles",
    "name": "The Beatles",
    "domain": "Music",
    "sort_order": 102
  },
  {
    "slug": "rock-and-roll",
    "name": "Rock & Roll",
    "domain": "Music",
    "sort_order": 103
  },
  {
    "slug": "jazz",
    "name": "Jazz",
    "domain": "Music",
    "sort_order": 104
  },
  {
    "slug": "hip-hop",
    "name": "Hip-Hop",
    "domain": "Music",
    "sort_order": 105
  },
  {
    "slug": "pop-music",
    "name": "Pop Music",
    "domain": "Music",
    "sort_order": 106
  },
  {
    "slug": "country-music",
    "name": "Country Music",
    "domain": "Music",
    "sort_order": 107
  },
  {
    "slug": "opera",
    "name": "Opera",
    "domain": "Music",
    "sort_order": 108
  },
  {
    "slug": "music-theory",
    "name": "Music Theory",
    "domain": "Music",
    "sort_order": 109
  },
  {
    "slug": "musical-instruments",
    "name": "Musical Instruments",
    "domain": "Music",
    "sort_order": 110
  },
  {
    "slug": "electronic-music",
    "name": "Electronic Music",
    "domain": "Music",
    "sort_order": 111
  },
  {
    "slug": "grammy-awards",
    "name": "Grammy Awards",
    "domain": "Music",
    "sort_order": 112
  },
  {
    "slug": "music-of-the-1980s",
    "name": "Music of the 1980s",
    "domain": "Music",
    "sort_order": 113
  },
  {
    "slug": "reggae",
    "name": "Reggae",
    "domain": "Music",
    "sort_order": 114
  },
  {
    "slug": "blues",
    "name": "Blues",
    "domain": "Music",
    "sort_order": 115
  },
  {
    "slug": "folk-music",
    "name": "Folk Music",
    "domain": "Music",
    "sort_order": 116
  },
  {
    "slug": "broadway-and-musicals",
    "name": "Broadway & Musicals",
    "domain": "Music",
    "sort_order": 117
  },
  {
    "slug": "album-covers",
    "name": "Album Covers",
    "domain": "Music",
    "sort_order": 118
  },
  {
    "slug": "one-hit-wonders",
    "name": "One-Hit Wonders",
    "domain": "Music",
    "sort_order": 119
  },
  {
    "slug": "world-music",
    "name": "World Music",
    "domain": "Music",
    "sort_order": 120
  },
  {
    "slug": "the-olympic-games",
    "name": "The Olympic Games",
    "domain": "Sports",
    "sort_order": 121
  },
  {
    "slug": "association-football",
    "name": "Association Football",
    "domain": "Sports",
    "sort_order": 122
  },
  {
    "slug": "basketball",
    "name": "Basketball",
    "domain": "Sports",
    "sort_order": 123
  },
  {
    "slug": "american-football",
    "name": "American Football",
    "domain": "Sports",
    "sort_order": 124
  },
  {
    "slug": "baseball",
    "name": "Baseball",
    "domain": "Sports",
    "sort_order": 125
  },
  {
    "slug": "tennis",
    "name": "Tennis",
    "domain": "Sports",
    "sort_order": 126
  },
  {
    "slug": "golf",
    "name": "Golf",
    "domain": "Sports",
    "sort_order": 127
  },
  {
    "slug": "cricket",
    "name": "Cricket",
    "domain": "Sports",
    "sort_order": 128
  },
  {
    "slug": "formula-1",
    "name": "Formula 1",
    "domain": "Sports",
    "sort_order": 129
  },
  {
    "slug": "boxing",
    "name": "Boxing",
    "domain": "Sports",
    "sort_order": 130
  },
  {
    "slug": "the-fifa-world-cup",
    "name": "The FIFA World Cup",
    "domain": "Sports",
    "sort_order": 131
  },
  {
    "slug": "ice-hockey",
    "name": "Ice Hockey",
    "domain": "Sports",
    "sort_order": 132
  },
  {
    "slug": "rugby",
    "name": "Rugby",
    "domain": "Sports",
    "sort_order": 133
  },
  {
    "slug": "athletics-and-track",
    "name": "Athletics & Track",
    "domain": "Sports",
    "sort_order": 134
  },
  {
    "slug": "swimming",
    "name": "Swimming",
    "domain": "Sports",
    "sort_order": 135
  },
  {
    "slug": "cycling",
    "name": "Cycling",
    "domain": "Sports",
    "sort_order": 136
  },
  {
    "slug": "martial-arts",
    "name": "Martial Arts",
    "domain": "Sports",
    "sort_order": 137
  },
  {
    "slug": "winter-sports",
    "name": "Winter Sports",
    "domain": "Sports",
    "sort_order": 138
  },
  {
    "slug": "sports-records",
    "name": "Sports Records",
    "domain": "Sports",
    "sort_order": 139
  },
  {
    "slug": "sports-halls-of-fame",
    "name": "Sports Halls of Fame",
    "domain": "Sports",
    "sort_order": 140
  },
  {
    "slug": "renaissance-art",
    "name": "Renaissance Art",
    "domain": "Art & Architecture",
    "sort_order": 141
  },
  {
    "slug": "impressionism",
    "name": "Impressionism",
    "domain": "Art & Architecture",
    "sort_order": 142
  },
  {
    "slug": "modern-art",
    "name": "Modern Art",
    "domain": "Art & Architecture",
    "sort_order": 143
  },
  {
    "slug": "famous-paintings",
    "name": "Famous Paintings",
    "domain": "Art & Architecture",
    "sort_order": 144
  },
  {
    "slug": "sculpture",
    "name": "Sculpture",
    "domain": "Art & Architecture",
    "sort_order": 145
  },
  {
    "slug": "gothic-architecture",
    "name": "Gothic Architecture",
    "domain": "Art & Architecture",
    "sort_order": 146
  },
  {
    "slug": "ancient-architecture",
    "name": "Ancient Architecture",
    "domain": "Art & Architecture",
    "sort_order": 147
  },
  {
    "slug": "surrealism",
    "name": "Surrealism",
    "domain": "Art & Architecture",
    "sort_order": 148
  },
  {
    "slug": "photography",
    "name": "Photography",
    "domain": "Art & Architecture",
    "sort_order": 149
  },
  {
    "slug": "pop-art",
    "name": "Pop Art",
    "domain": "Art & Architecture",
    "sort_order": 150
  },
  {
    "slug": "baroque-art",
    "name": "Baroque Art",
    "domain": "Art & Architecture",
    "sort_order": 151
  },
  {
    "slug": "street-art",
    "name": "Street Art",
    "domain": "Art & Architecture",
    "sort_order": 152
  },
  {
    "slug": "architectural-styles",
    "name": "Architectural Styles",
    "domain": "Art & Architecture",
    "sort_order": 153
  },
  {
    "slug": "famous-museums",
    "name": "Famous Museums",
    "domain": "Art & Architecture",
    "sort_order": 154
  },
  {
    "slug": "cubism",
    "name": "Cubism",
    "domain": "Art & Architecture",
    "sort_order": 155
  },
  {
    "slug": "art-movements",
    "name": "Art Movements",
    "domain": "Art & Architecture",
    "sort_order": 156
  },
  {
    "slug": "pottery-and-ceramics",
    "name": "Pottery & Ceramics",
    "domain": "Art & Architecture",
    "sort_order": 157
  },
  {
    "slug": "skyscrapers",
    "name": "Skyscrapers",
    "domain": "Art & Architecture",
    "sort_order": 158
  },
  {
    "slug": "bridges-and-landmarks",
    "name": "Bridges & Landmarks",
    "domain": "Art & Architecture",
    "sort_order": 159
  },
  {
    "slug": "color-and-design",
    "name": "Color & Design",
    "domain": "Art & Architecture",
    "sort_order": 160
  },
  {
    "slug": "computer-history",
    "name": "Computer History",
    "domain": "Technology & Computing",
    "sort_order": 161
  },
  {
    "slug": "programming-languages",
    "name": "Programming Languages",
    "domain": "Technology & Computing",
    "sort_order": 162
  },
  {
    "slug": "the-internet",
    "name": "The Internet",
    "domain": "Technology & Computing",
    "sort_order": 163
  },
  {
    "slug": "artificial-intelligence",
    "name": "Artificial Intelligence",
    "domain": "Technology & Computing",
    "sort_order": 164
  },
  {
    "slug": "operating-systems",
    "name": "Operating Systems",
    "domain": "Technology & Computing",
    "sort_order": 165
  },
  {
    "slug": "cybersecurity",
    "name": "Cybersecurity",
    "domain": "Technology & Computing",
    "sort_order": 166
  },
  {
    "slug": "social-media",
    "name": "Social Media",
    "domain": "Technology & Computing",
    "sort_order": 167
  },
  {
    "slug": "smartphones",
    "name": "Smartphones",
    "domain": "Technology & Computing",
    "sort_order": 168
  },
  {
    "slug": "cryptography",
    "name": "Cryptography",
    "domain": "Technology & Computing",
    "sort_order": 169
  },
  {
    "slug": "video-game-consoles",
    "name": "Video Game Consoles",
    "domain": "Technology & Computing",
    "sort_order": 170
  },
  {
    "slug": "tech-companies",
    "name": "Tech Companies",
    "domain": "Technology & Computing",
    "sort_order": 171
  },
  {
    "slug": "hardware-and-processors",
    "name": "Hardware & Processors",
    "domain": "Technology & Computing",
    "sort_order": 172
  },
  {
    "slug": "databases",
    "name": "Databases",
    "domain": "Technology & Computing",
    "sort_order": 173
  },
  {
    "slug": "robotics",
    "name": "Robotics",
    "domain": "Technology & Computing",
    "sort_order": 174
  },
  {
    "slug": "the-world-wide-web",
    "name": "The World Wide Web",
    "domain": "Technology & Computing",
    "sort_order": 175
  },
  {
    "slug": "open-source-software",
    "name": "Open Source Software",
    "domain": "Technology & Computing",
    "sort_order": 176
  },
  {
    "slug": "silicon-valley",
    "name": "Silicon Valley",
    "domain": "Technology & Computing",
    "sort_order": 177
  },
  {
    "slug": "coding-concepts",
    "name": "Coding Concepts",
    "domain": "Technology & Computing",
    "sort_order": 178
  },
  {
    "slug": "computer-networking",
    "name": "Computer Networking",
    "domain": "Technology & Computing",
    "sort_order": 179
  },
  {
    "slug": "cryptocurrency-and-blockchain",
    "name": "Cryptocurrency & Blockchain",
    "domain": "Technology & Computing",
    "sort_order": 180
  },
  {
    "slug": "world-cuisines",
    "name": "World Cuisines",
    "domain": "Food & Drink",
    "sort_order": 181
  },
  {
    "slug": "wine",
    "name": "Wine",
    "domain": "Food & Drink",
    "sort_order": 182
  },
  {
    "slug": "cheese",
    "name": "Cheese",
    "domain": "Food & Drink",
    "sort_order": 183
  },
  {
    "slug": "coffee",
    "name": "Coffee",
    "domain": "Food & Drink",
    "sort_order": 184
  },
  {
    "slug": "spices-and-herbs",
    "name": "Spices & Herbs",
    "domain": "Food & Drink",
    "sort_order": 185
  },
  {
    "slug": "desserts",
    "name": "Desserts",
    "domain": "Food & Drink",
    "sort_order": 186
  },
  {
    "slug": "cocktails",
    "name": "Cocktails",
    "domain": "Food & Drink",
    "sort_order": 187
  },
  {
    "slug": "beer-and-brewing",
    "name": "Beer & Brewing",
    "domain": "Food & Drink",
    "sort_order": 188
  },
  {
    "slug": "italian-cuisine",
    "name": "Italian Cuisine",
    "domain": "Food & Drink",
    "sort_order": 189
  },
  {
    "slug": "french-cuisine",
    "name": "French Cuisine",
    "domain": "Food & Drink",
    "sort_order": 190
  },
  {
    "slug": "asian-cuisine",
    "name": "Asian Cuisine",
    "domain": "Food & Drink",
    "sort_order": 191
  },
  {
    "slug": "street-food",
    "name": "Street Food",
    "domain": "Food & Drink",
    "sort_order": 192
  },
  {
    "slug": "cooking-techniques",
    "name": "Cooking Techniques",
    "domain": "Food & Drink",
    "sort_order": 193
  },
  {
    "slug": "fruits-and-vegetables",
    "name": "Fruits & Vegetables",
    "domain": "Food & Drink",
    "sort_order": 194
  },
  {
    "slug": "tea",
    "name": "Tea",
    "domain": "Food & Drink",
    "sort_order": 195
  },
  {
    "slug": "baking-and-pastry",
    "name": "Baking & Pastry",
    "domain": "Food & Drink",
    "sort_order": 196
  },
  {
    "slug": "fast-food",
    "name": "Fast Food",
    "domain": "Food & Drink",
    "sort_order": 197
  },
  {
    "slug": "famous-chefs",
    "name": "Famous Chefs",
    "domain": "Food & Drink",
    "sort_order": 198
  },
  {
    "slug": "food-history",
    "name": "Food History",
    "domain": "Food & Drink",
    "sort_order": 199
  },
  {
    "slug": "condiments-and-sauces",
    "name": "Condiments & Sauces",
    "domain": "Food & Drink",
    "sort_order": 200
  },
  {
    "slug": "sitcoms",
    "name": "Sitcoms",
    "domain": "Television",
    "sort_order": 201
  },
  {
    "slug": "drama-series",
    "name": "Drama Series",
    "domain": "Television",
    "sort_order": 202
  },
  {
    "slug": "reality-tv",
    "name": "Reality TV",
    "domain": "Television",
    "sort_order": 203
  },
  {
    "slug": "animated-series",
    "name": "Animated Series",
    "domain": "Television",
    "sort_order": 204
  },
  {
    "slug": "british-tv",
    "name": "British TV",
    "domain": "Television",
    "sort_order": 205
  },
  {
    "slug": "game-shows",
    "name": "Game Shows",
    "domain": "Television",
    "sort_order": 206
  },
  {
    "slug": "sci-fi-and-fantasy-tv",
    "name": "Sci-Fi & Fantasy TV",
    "domain": "Television",
    "sort_order": 207
  },
  {
    "slug": "crime-dramas",
    "name": "Crime Dramas",
    "domain": "Television",
    "sort_order": 208
  },
  {
    "slug": "tv-comedies",
    "name": "TV Comedies",
    "domain": "Television",
    "sort_order": 209
  },
  {
    "slug": "streaming-originals",
    "name": "Streaming Originals",
    "domain": "Television",
    "sort_order": 210
  },
  {
    "slug": "soap-operas",
    "name": "Soap Operas",
    "domain": "Television",
    "sort_order": 211
  },
  {
    "slug": "talk-shows",
    "name": "Talk Shows",
    "domain": "Television",
    "sort_order": 212
  },
  {
    "slug": "tv-theme-songs",
    "name": "TV Theme Songs",
    "domain": "Television",
    "sort_order": 213
  },
  {
    "slug": "anime",
    "name": "Anime",
    "domain": "Television",
    "sort_order": 214
  },
  {
    "slug": "tv-catchphrases",
    "name": "TV Catchphrases",
    "domain": "Television",
    "sort_order": 215
  },
  {
    "slug": "emmy-winners",
    "name": "Emmy Winners",
    "domain": "Television",
    "sort_order": 216
  },
  {
    "slug": "cartoon-classics",
    "name": "Cartoon Classics",
    "domain": "Television",
    "sort_order": 217
  },
  {
    "slug": "miniseries",
    "name": "Miniseries",
    "domain": "Television",
    "sort_order": 218
  },
  {
    "slug": "tv-hosts",
    "name": "TV Hosts",
    "domain": "Television",
    "sort_order": 219
  },
  {
    "slug": "television-history",
    "name": "Television History",
    "domain": "Television",
    "sort_order": 220
  },
  {
    "slug": "nintendo",
    "name": "Nintendo",
    "domain": "Video Games",
    "sort_order": 221
  },
  {
    "slug": "playstation",
    "name": "PlayStation",
    "domain": "Video Games",
    "sort_order": 222
  },
  {
    "slug": "retro-arcade-games",
    "name": "Retro Arcade Games",
    "domain": "Video Games",
    "sort_order": 223
  },
  {
    "slug": "role-playing-games",
    "name": "Role-Playing Games",
    "domain": "Video Games",
    "sort_order": 224
  },
  {
    "slug": "first-person-shooters",
    "name": "First-Person Shooters",
    "domain": "Video Games",
    "sort_order": 225
  },
  {
    "slug": "indie-games",
    "name": "Indie Games",
    "domain": "Video Games",
    "sort_order": 226
  },
  {
    "slug": "esports",
    "name": "Esports",
    "domain": "Video Games",
    "sort_order": 227
  },
  {
    "slug": "game-franchises",
    "name": "Game Franchises",
    "domain": "Video Games",
    "sort_order": 228
  },
  {
    "slug": "fighting-games",
    "name": "Fighting Games",
    "domain": "Video Games",
    "sort_order": 229
  },
  {
    "slug": "strategy-games",
    "name": "Strategy Games",
    "domain": "Video Games",
    "sort_order": 230
  },
  {
    "slug": "open-world-games",
    "name": "Open-World Games",
    "domain": "Video Games",
    "sort_order": 231
  },
  {
    "slug": "the-mario-universe",
    "name": "The Mario Universe",
    "domain": "Video Games",
    "sort_order": 232
  },
  {
    "slug": "the-legend-of-zelda",
    "name": "The Legend of Zelda",
    "domain": "Video Games",
    "sort_order": 233
  },
  {
    "slug": "pokemon",
    "name": "Pokemon",
    "domain": "Video Games",
    "sort_order": 234
  },
  {
    "slug": "minecraft",
    "name": "Minecraft",
    "domain": "Video Games",
    "sort_order": 235
  },
  {
    "slug": "game-developers",
    "name": "Game Developers",
    "domain": "Video Games",
    "sort_order": 236
  },
  {
    "slug": "gaming-hardware",
    "name": "Gaming Hardware",
    "domain": "Video Games",
    "sort_order": 237
  },
  {
    "slug": "puzzle-games",
    "name": "Puzzle Games",
    "domain": "Video Games",
    "sort_order": 238
  },
  {
    "slug": "mmorpgs",
    "name": "MMORPGs",
    "domain": "Video Games",
    "sort_order": 239
  },
  {
    "slug": "video-game-music",
    "name": "Video Game Music",
    "domain": "Video Games",
    "sort_order": 240
  },
  {
    "slug": "greek-mythology",
    "name": "Greek Mythology",
    "domain": "Mythology & Religion",
    "sort_order": 241
  },
  {
    "slug": "norse-mythology",
    "name": "Norse Mythology",
    "domain": "Mythology & Religion",
    "sort_order": 242
  },
  {
    "slug": "egyptian-mythology",
    "name": "Egyptian Mythology",
    "domain": "Mythology & Religion",
    "sort_order": 243
  },
  {
    "slug": "roman-mythology",
    "name": "Roman Mythology",
    "domain": "Mythology & Religion",
    "sort_order": 244
  },
  {
    "slug": "world-religions",
    "name": "World Religions",
    "domain": "Mythology & Religion",
    "sort_order": 245
  },
  {
    "slug": "christianity",
    "name": "Christianity",
    "domain": "Mythology & Religion",
    "sort_order": 246
  },
  {
    "slug": "islam",
    "name": "Islam",
    "domain": "Mythology & Religion",
    "sort_order": 247
  },
  {
    "slug": "hinduism",
    "name": "Hinduism",
    "domain": "Mythology & Religion",
    "sort_order": 248
  },
  {
    "slug": "buddhism",
    "name": "Buddhism",
    "domain": "Mythology & Religion",
    "sort_order": 249
  },
  {
    "slug": "judaism",
    "name": "Judaism",
    "domain": "Mythology & Religion",
    "sort_order": 250
  },
  {
    "slug": "celtic-mythology",
    "name": "Celtic Mythology",
    "domain": "Mythology & Religion",
    "sort_order": 251
  },
  {
    "slug": "japanese-folklore",
    "name": "Japanese Folklore",
    "domain": "Mythology & Religion",
    "sort_order": 252
  },
  {
    "slug": "legendary-creatures",
    "name": "Legendary Creatures",
    "domain": "Mythology & Religion",
    "sort_order": 253
  },
  {
    "slug": "biblical-stories",
    "name": "Biblical Stories",
    "domain": "Mythology & Religion",
    "sort_order": 254
  },
  {
    "slug": "gods-and-goddesses",
    "name": "Gods & Goddesses",
    "domain": "Mythology & Religion",
    "sort_order": 255
  },
  {
    "slug": "sacred-texts",
    "name": "Sacred Texts",
    "domain": "Mythology & Religion",
    "sort_order": 256
  },
  {
    "slug": "mythological-heroes",
    "name": "Mythological Heroes",
    "domain": "Mythology & Religion",
    "sort_order": 257
  },
  {
    "slug": "afterlife-beliefs",
    "name": "Afterlife Beliefs",
    "domain": "Mythology & Religion",
    "sort_order": 258
  },
  {
    "slug": "rituals-and-festivals",
    "name": "Rituals & Festivals",
    "domain": "Mythology & Religion",
    "sort_order": 259
  },
  {
    "slug": "creation-myths",
    "name": "Creation Myths",
    "domain": "Mythology & Religion",
    "sort_order": 260
  },
  {
    "slug": "world-leaders",
    "name": "World Leaders",
    "domain": "Politics & Law",
    "sort_order": 261
  },
  {
    "slug": "u-s-presidents",
    "name": "U.S. Presidents",
    "domain": "Politics & Law",
    "sort_order": 262
  },
  {
    "slug": "political-systems",
    "name": "Political Systems",
    "domain": "Politics & Law",
    "sort_order": 263
  },
  {
    "slug": "the-united-nations",
    "name": "The United Nations",
    "domain": "Politics & Law",
    "sort_order": 264
  },
  {
    "slug": "constitutions",
    "name": "Constitutions",
    "domain": "Politics & Law",
    "sort_order": 265
  },
  {
    "slug": "elections-and-voting",
    "name": "Elections & Voting",
    "domain": "Politics & Law",
    "sort_order": 266
  },
  {
    "slug": "supreme-court-cases",
    "name": "Supreme Court Cases",
    "domain": "Politics & Law",
    "sort_order": 267
  },
  {
    "slug": "international-treaties",
    "name": "International Treaties",
    "domain": "Politics & Law",
    "sort_order": 268
  },
  {
    "slug": "human-rights",
    "name": "Human Rights",
    "domain": "Politics & Law",
    "sort_order": 269
  },
  {
    "slug": "political-ideologies",
    "name": "Political Ideologies",
    "domain": "Politics & Law",
    "sort_order": 270
  },
  {
    "slug": "monarchies",
    "name": "Monarchies",
    "domain": "Politics & Law",
    "sort_order": 271
  },
  {
    "slug": "diplomacy",
    "name": "Diplomacy",
    "domain": "Politics & Law",
    "sort_order": 272
  },
  {
    "slug": "legal-systems",
    "name": "Legal Systems",
    "domain": "Politics & Law",
    "sort_order": 273
  },
  {
    "slug": "famous-trials",
    "name": "Famous Trials",
    "domain": "Politics & Law",
    "sort_order": 274
  },
  {
    "slug": "political-scandals",
    "name": "Political Scandals",
    "domain": "Politics & Law",
    "sort_order": 275
  },
  {
    "slug": "prime-ministers",
    "name": "Prime Ministers",
    "domain": "Politics & Law",
    "sort_order": 276
  },
  {
    "slug": "revolutions-and-movements",
    "name": "Revolutions & Movements",
    "domain": "Politics & Law",
    "sort_order": 277
  },
  {
    "slug": "branches-of-government",
    "name": "Branches of Government",
    "domain": "Politics & Law",
    "sort_order": 278
  },
  {
    "slug": "espionage",
    "name": "Espionage",
    "domain": "Politics & Law",
    "sort_order": 279
  },
  {
    "slug": "landmark-legislation",
    "name": "Landmark Legislation",
    "domain": "Politics & Law",
    "sort_order": 280
  },
  {
    "slug": "stock-markets",
    "name": "Stock Markets",
    "domain": "Business & Economics",
    "sort_order": 281
  },
  {
    "slug": "famous-entrepreneurs",
    "name": "Famous Entrepreneurs",
    "domain": "Business & Economics",
    "sort_order": 282
  },
  {
    "slug": "global-brands",
    "name": "Global Brands",
    "domain": "Business & Economics",
    "sort_order": 283
  },
  {
    "slug": "economic-theory",
    "name": "Economic Theory",
    "domain": "Business & Economics",
    "sort_order": 284
  },
  {
    "slug": "currencies",
    "name": "Currencies",
    "domain": "Business & Economics",
    "sort_order": 285
  },
  {
    "slug": "marketing-and-advertising",
    "name": "Marketing & Advertising",
    "domain": "Business & Economics",
    "sort_order": 286
  },
  {
    "slug": "startups",
    "name": "Startups",
    "domain": "Business & Economics",
    "sort_order": 287
  },
  {
    "slug": "banking",
    "name": "Banking",
    "domain": "Business & Economics",
    "sort_order": 288
  },
  {
    "slug": "trade-and-commerce",
    "name": "Trade & Commerce",
    "domain": "Business & Economics",
    "sort_order": 289
  },
  {
    "slug": "fortune-500-companies",
    "name": "Fortune 500 Companies",
    "domain": "Business & Economics",
    "sort_order": 290
  },
  {
    "slug": "supply-and-demand",
    "name": "Supply & Demand",
    "domain": "Business & Economics",
    "sort_order": 291
  },
  {
    "slug": "inflation-and-recession",
    "name": "Inflation & Recession",
    "domain": "Business & Economics",
    "sort_order": 292
  },
  {
    "slug": "corporate-logos",
    "name": "Corporate Logos",
    "domain": "Business & Economics",
    "sort_order": 293
  },
  {
    "slug": "billionaires",
    "name": "Billionaires",
    "domain": "Business & Economics",
    "sort_order": 294
  },
  {
    "slug": "management-and-leadership",
    "name": "Management & Leadership",
    "domain": "Business & Economics",
    "sort_order": 295
  },
  {
    "slug": "real-estate",
    "name": "Real Estate",
    "domain": "Business & Economics",
    "sort_order": 296
  },
  {
    "slug": "mergers-and-acquisitions",
    "name": "Mergers & Acquisitions",
    "domain": "Business & Economics",
    "sort_order": 297
  },
  {
    "slug": "retail-and-shopping",
    "name": "Retail & Shopping",
    "domain": "Business & Economics",
    "sort_order": 298
  },
  {
    "slug": "economic-history",
    "name": "Economic History",
    "domain": "Business & Economics",
    "sort_order": 299
  },
  {
    "slug": "personal-finance",
    "name": "Personal Finance",
    "domain": "Business & Economics",
    "sort_order": 300
  },
  {
    "slug": "the-solar-system",
    "name": "The Solar System",
    "domain": "Space & Astronomy",
    "sort_order": 301
  },
  {
    "slug": "the-planets",
    "name": "The Planets",
    "domain": "Space & Astronomy",
    "sort_order": 302
  },
  {
    "slug": "stars-and-constellations",
    "name": "Stars & Constellations",
    "domain": "Space & Astronomy",
    "sort_order": 303
  },
  {
    "slug": "galaxies",
    "name": "Galaxies",
    "domain": "Space & Astronomy",
    "sort_order": 304
  },
  {
    "slug": "space-missions",
    "name": "Space Missions",
    "domain": "Space & Astronomy",
    "sort_order": 305
  },
  {
    "slug": "the-moon",
    "name": "The Moon",
    "domain": "Space & Astronomy",
    "sort_order": 306
  },
  {
    "slug": "black-holes",
    "name": "Black Holes",
    "domain": "Space & Astronomy",
    "sort_order": 307
  },
  {
    "slug": "the-sun",
    "name": "The Sun",
    "domain": "Space & Astronomy",
    "sort_order": 308
  },
  {
    "slug": "astronauts",
    "name": "Astronauts",
    "domain": "Space & Astronomy",
    "sort_order": 309
  },
  {
    "slug": "telescopes",
    "name": "Telescopes",
    "domain": "Space & Astronomy",
    "sort_order": 310
  },
  {
    "slug": "comets-and-asteroids",
    "name": "Comets & Asteroids",
    "domain": "Space & Astronomy",
    "sort_order": 311
  },
  {
    "slug": "nasa",
    "name": "NASA",
    "domain": "Space & Astronomy",
    "sort_order": 312
  },
  {
    "slug": "the-big-bang",
    "name": "The Big Bang",
    "domain": "Space & Astronomy",
    "sort_order": 313
  },
  {
    "slug": "exoplanets",
    "name": "Exoplanets",
    "domain": "Space & Astronomy",
    "sort_order": 314
  },
  {
    "slug": "rockets-and-spaceflight",
    "name": "Rockets & Spaceflight",
    "domain": "Space & Astronomy",
    "sort_order": 315
  },
  {
    "slug": "mars-exploration",
    "name": "Mars Exploration",
    "domain": "Space & Astronomy",
    "sort_order": 316
  },
  {
    "slug": "the-space-station",
    "name": "The Space Station",
    "domain": "Space & Astronomy",
    "sort_order": 317
  },
  {
    "slug": "cosmology",
    "name": "Cosmology",
    "domain": "Space & Astronomy",
    "sort_order": 318
  },
  {
    "slug": "nebulae",
    "name": "Nebulae",
    "domain": "Space & Astronomy",
    "sort_order": 319
  },
  {
    "slug": "space-agencies",
    "name": "Space Agencies",
    "domain": "Space & Astronomy",
    "sort_order": 320
  },
  {
    "slug": "mammals",
    "name": "Mammals",
    "domain": "Animals & Wildlife",
    "sort_order": 321
  },
  {
    "slug": "birds",
    "name": "Birds",
    "domain": "Animals & Wildlife",
    "sort_order": 322
  },
  {
    "slug": "reptiles-and-amphibians",
    "name": "Reptiles & Amphibians",
    "domain": "Animals & Wildlife",
    "sort_order": 323
  },
  {
    "slug": "fish-and-marine-life",
    "name": "Fish & Marine Life",
    "domain": "Animals & Wildlife",
    "sort_order": 324
  },
  {
    "slug": "insects",
    "name": "Insects",
    "domain": "Animals & Wildlife",
    "sort_order": 325
  },
  {
    "slug": "dinosaurs",
    "name": "Dinosaurs",
    "domain": "Animals & Wildlife",
    "sort_order": 326
  },
  {
    "slug": "endangered-species",
    "name": "Endangered Species",
    "domain": "Animals & Wildlife",
    "sort_order": 327
  },
  {
    "slug": "big-cats",
    "name": "Big Cats",
    "domain": "Animals & Wildlife",
    "sort_order": 328
  },
  {
    "slug": "primates",
    "name": "Primates",
    "domain": "Animals & Wildlife",
    "sort_order": 329
  },
  {
    "slug": "ocean-predators",
    "name": "Ocean Predators",
    "domain": "Animals & Wildlife",
    "sort_order": 330
  },
  {
    "slug": "pets-and-domestic-animals",
    "name": "Pets & Domestic Animals",
    "domain": "Animals & Wildlife",
    "sort_order": 331
  },
  {
    "slug": "animal-behavior",
    "name": "Animal Behavior",
    "domain": "Animals & Wildlife",
    "sort_order": 332
  },
  {
    "slug": "migration-and-hibernation",
    "name": "Migration & Hibernation",
    "domain": "Animals & Wildlife",
    "sort_order": 333
  },
  {
    "slug": "rainforest-animals",
    "name": "Rainforest Animals",
    "domain": "Animals & Wildlife",
    "sort_order": 334
  },
  {
    "slug": "polar-wildlife",
    "name": "Polar Wildlife",
    "domain": "Animals & Wildlife",
    "sort_order": 335
  },
  {
    "slug": "venomous-animals",
    "name": "Venomous Animals",
    "domain": "Animals & Wildlife",
    "sort_order": 336
  },
  {
    "slug": "animal-classification",
    "name": "Animal Classification",
    "domain": "Animals & Wildlife",
    "sort_order": 337
  },
  {
    "slug": "extinct-animals",
    "name": "Extinct Animals",
    "domain": "Animals & Wildlife",
    "sort_order": 338
  },
  {
    "slug": "deep-sea-creatures",
    "name": "Deep Sea Creatures",
    "domain": "Animals & Wildlife",
    "sort_order": 339
  },
  {
    "slug": "wildlife-conservation",
    "name": "Wildlife Conservation",
    "domain": "Animals & Wildlife",
    "sort_order": 340
  },
  {
    "slug": "human-anatomy",
    "name": "Human Anatomy",
    "domain": "Human Body & Medicine",
    "sort_order": 341
  },
  {
    "slug": "the-circulatory-system",
    "name": "The Circulatory System",
    "domain": "Human Body & Medicine",
    "sort_order": 342
  },
  {
    "slug": "the-nervous-system",
    "name": "The Nervous System",
    "domain": "Human Body & Medicine",
    "sort_order": 343
  },
  {
    "slug": "the-immune-system",
    "name": "The Immune System",
    "domain": "Human Body & Medicine",
    "sort_order": 344
  },
  {
    "slug": "diseases-and-disorders",
    "name": "Diseases & Disorders",
    "domain": "Human Body & Medicine",
    "sort_order": 345
  },
  {
    "slug": "vaccines",
    "name": "Vaccines",
    "domain": "Human Body & Medicine",
    "sort_order": 346
  },
  {
    "slug": "medical-history",
    "name": "Medical History",
    "domain": "Human Body & Medicine",
    "sort_order": 347
  },
  {
    "slug": "surgery",
    "name": "Surgery",
    "domain": "Human Body & Medicine",
    "sort_order": 348
  },
  {
    "slug": "pharmacology",
    "name": "Pharmacology",
    "domain": "Human Body & Medicine",
    "sort_order": 349
  },
  {
    "slug": "nutrition",
    "name": "Nutrition",
    "domain": "Human Body & Medicine",
    "sort_order": 350
  },
  {
    "slug": "the-brain",
    "name": "The Brain",
    "domain": "Human Body & Medicine",
    "sort_order": 351
  },
  {
    "slug": "genetics-and-heredity",
    "name": "Genetics & Heredity",
    "domain": "Human Body & Medicine",
    "sort_order": 352
  },
  {
    "slug": "bones-and-skeleton",
    "name": "Bones & Skeleton",
    "domain": "Human Body & Medicine",
    "sort_order": 353
  },
  {
    "slug": "the-digestive-system",
    "name": "The Digestive System",
    "domain": "Human Body & Medicine",
    "sort_order": 354
  },
  {
    "slug": "mental-health",
    "name": "Mental Health",
    "domain": "Human Body & Medicine",
    "sort_order": 355
  },
  {
    "slug": "pandemics",
    "name": "Pandemics",
    "domain": "Human Body & Medicine",
    "sort_order": 356
  },
  {
    "slug": "famous-physicians",
    "name": "Famous Physicians",
    "domain": "Human Body & Medicine",
    "sort_order": 357
  },
  {
    "slug": "blood-and-blood-types",
    "name": "Blood & Blood Types",
    "domain": "Human Body & Medicine",
    "sort_order": 358
  },
  {
    "slug": "the-five-senses",
    "name": "The Five Senses",
    "domain": "Human Body & Medicine",
    "sort_order": 359
  },
  {
    "slug": "medical-breakthroughs",
    "name": "Medical Breakthroughs",
    "domain": "Human Body & Medicine",
    "sort_order": 360
  },
  {
    "slug": "etymology",
    "name": "Etymology",
    "domain": "Language & Words",
    "sort_order": 361
  },
  {
    "slug": "idioms-and-phrases",
    "name": "Idioms & Phrases",
    "domain": "Language & Words",
    "sort_order": 362
  },
  {
    "slug": "foreign-languages",
    "name": "Foreign Languages",
    "domain": "Language & Words",
    "sort_order": 363
  },
  {
    "slug": "grammar",
    "name": "Grammar",
    "domain": "Language & Words",
    "sort_order": 364
  },
  {
    "slug": "latin-and-greek-roots",
    "name": "Latin & Greek Roots",
    "domain": "Language & Words",
    "sort_order": 365
  },
  {
    "slug": "english-vocabulary",
    "name": "English Vocabulary",
    "domain": "Language & Words",
    "sort_order": 366
  },
  {
    "slug": "sign-language",
    "name": "Sign Language",
    "domain": "Language & Words",
    "sort_order": 367
  },
  {
    "slug": "writing-systems",
    "name": "Writing Systems",
    "domain": "Language & Words",
    "sort_order": 368
  },
  {
    "slug": "slang-and-dialects",
    "name": "Slang & Dialects",
    "domain": "Language & Words",
    "sort_order": 369
  },
  {
    "slug": "palindromes-and-wordplay",
    "name": "Palindromes & Wordplay",
    "domain": "Language & Words",
    "sort_order": 370
  },
  {
    "slug": "loanwords",
    "name": "Loanwords",
    "domain": "Language & Words",
    "sort_order": 371
  },
  {
    "slug": "dead-languages",
    "name": "Dead Languages",
    "domain": "Language & Words",
    "sort_order": 372
  },
  {
    "slug": "alphabets",
    "name": "Alphabets",
    "domain": "Language & Words",
    "sort_order": 373
  },
  {
    "slug": "translation",
    "name": "Translation",
    "domain": "Language & Words",
    "sort_order": 374
  },
  {
    "slug": "linguistics",
    "name": "Linguistics",
    "domain": "Language & Words",
    "sort_order": 375
  },
  {
    "slug": "onomatopoeia",
    "name": "Onomatopoeia",
    "domain": "Language & Words",
    "sort_order": 376
  },
  {
    "slug": "acronyms-and-abbreviations",
    "name": "Acronyms & Abbreviations",
    "domain": "Language & Words",
    "sort_order": 377
  },
  {
    "slug": "proverbs",
    "name": "Proverbs",
    "domain": "Language & Words",
    "sort_order": 378
  },
  {
    "slug": "rhyme-and-meter",
    "name": "Rhyme & Meter",
    "domain": "Language & Words",
    "sort_order": 379
  },
  {
    "slug": "constructed-languages",
    "name": "Constructed Languages",
    "domain": "Language & Words",
    "sort_order": 380
  },
  {
    "slug": "award-shows",
    "name": "Award Shows",
    "domain": "Pop Culture & Celebrities",
    "sort_order": 381
  },
  {
    "slug": "internet-memes",
    "name": "Internet Memes",
    "domain": "Pop Culture & Celebrities",
    "sort_order": 382
  },
  {
    "slug": "celebrity-couples",
    "name": "Celebrity Couples",
    "domain": "Pop Culture & Celebrities",
    "sort_order": 383
  },
  {
    "slug": "fashion-icons",
    "name": "Fashion Icons",
    "domain": "Pop Culture & Celebrities",
    "sort_order": 384
  },
  {
    "slug": "viral-moments",
    "name": "Viral Moments",
    "domain": "Pop Culture & Celebrities",
    "sort_order": 385
  },
  {
    "slug": "reality-stars",
    "name": "Reality Stars",
    "domain": "Pop Culture & Celebrities",
    "sort_order": 386
  },
  {
    "slug": "social-media-influencers",
    "name": "Social Media Influencers",
    "domain": "Pop Culture & Celebrities",
    "sort_order": 387
  },
  {
    "slug": "tabloid-history",
    "name": "Tabloid History",
    "domain": "Pop Culture & Celebrities",
    "sort_order": 388
  },
  {
    "slug": "red-carpet-fashion",
    "name": "Red Carpet Fashion",
    "domain": "Pop Culture & Celebrities",
    "sort_order": 389
  },
  {
    "slug": "celebrity-nicknames",
    "name": "Celebrity Nicknames",
    "domain": "Pop Culture & Celebrities",
    "sort_order": 390
  },
  {
    "slug": "boy-bands-and-girl-groups",
    "name": "Boy Bands & Girl Groups",
    "domain": "Pop Culture & Celebrities",
    "sort_order": 391
  },
  {
    "slug": "pop-culture-of-the-2000s",
    "name": "Pop Culture of the 2000s",
    "domain": "Pop Culture & Celebrities",
    "sort_order": 392
  },
  {
    "slug": "fandoms",
    "name": "Fandoms",
    "domain": "Pop Culture & Celebrities",
    "sort_order": 393
  },
  {
    "slug": "famous-catchphrases",
    "name": "Famous Catchphrases",
    "domain": "Pop Culture & Celebrities",
    "sort_order": 394
  },
  {
    "slug": "celebrity-feuds",
    "name": "Celebrity Feuds",
    "domain": "Pop Culture & Celebrities",
    "sort_order": 395
  },
  {
    "slug": "child-stars",
    "name": "Child Stars",
    "domain": "Pop Culture & Celebrities",
    "sort_order": 396
  },
  {
    "slug": "pop-culture-of-the-1990s",
    "name": "Pop Culture of the 1990s",
    "domain": "Pop Culture & Celebrities",
    "sort_order": 397
  },
  {
    "slug": "award-season",
    "name": "Award Season",
    "domain": "Pop Culture & Celebrities",
    "sort_order": 398
  },
  {
    "slug": "scandals-and-paparazzi",
    "name": "Scandals & Paparazzi",
    "domain": "Pop Culture & Celebrities",
    "sort_order": 399
  },
  {
    "slug": "cultural-trends",
    "name": "Cultural Trends",
    "domain": "Pop Culture & Celebrities",
    "sort_order": 400
  },
  {
    "slug": "arithmetic",
    "name": "Arithmetic",
    "domain": "Mathematics & Logic",
    "sort_order": 401
  },
  {
    "slug": "algebra",
    "name": "Algebra",
    "domain": "Mathematics & Logic",
    "sort_order": 402
  },
  {
    "slug": "geometry",
    "name": "Geometry",
    "domain": "Mathematics & Logic",
    "sort_order": 403
  },
  {
    "slug": "calculus",
    "name": "Calculus",
    "domain": "Mathematics & Logic",
    "sort_order": 404
  },
  {
    "slug": "prime-numbers",
    "name": "Prime Numbers",
    "domain": "Mathematics & Logic",
    "sort_order": 405
  },
  {
    "slug": "famous-mathematicians",
    "name": "Famous Mathematicians",
    "domain": "Mathematics & Logic",
    "sort_order": 406
  },
  {
    "slug": "probability",
    "name": "Probability",
    "domain": "Mathematics & Logic",
    "sort_order": 407
  },
  {
    "slug": "statistics",
    "name": "Statistics",
    "domain": "Mathematics & Logic",
    "sort_order": 408
  },
  {
    "slug": "number-theory",
    "name": "Number Theory",
    "domain": "Mathematics & Logic",
    "sort_order": 409
  },
  {
    "slug": "mathematical-constants",
    "name": "Mathematical Constants",
    "domain": "Mathematics & Logic",
    "sort_order": 410
  },
  {
    "slug": "logic-puzzles",
    "name": "Logic Puzzles",
    "domain": "Mathematics & Logic",
    "sort_order": 411
  },
  {
    "slug": "trigonometry",
    "name": "Trigonometry",
    "domain": "Mathematics & Logic",
    "sort_order": 412
  },
  {
    "slug": "fractals",
    "name": "Fractals",
    "domain": "Mathematics & Logic",
    "sort_order": 413
  },
  {
    "slug": "set-theory",
    "name": "Set Theory",
    "domain": "Mathematics & Logic",
    "sort_order": 414
  },
  {
    "slug": "pi-and-circles",
    "name": "Pi & Circles",
    "domain": "Mathematics & Logic",
    "sort_order": 415
  },
  {
    "slug": "mathematical-proofs",
    "name": "Mathematical Proofs",
    "domain": "Mathematics & Logic",
    "sort_order": 416
  },
  {
    "slug": "sequences-and-series",
    "name": "Sequences & Series",
    "domain": "Mathematics & Logic",
    "sort_order": 417
  },
  {
    "slug": "topology",
    "name": "Topology",
    "domain": "Mathematics & Logic",
    "sort_order": 418
  },
  {
    "slug": "game-theory",
    "name": "Game Theory",
    "domain": "Mathematics & Logic",
    "sort_order": 419
  },
  {
    "slug": "ancient-mathematics",
    "name": "Ancient Mathematics",
    "domain": "Mathematics & Logic",
    "sort_order": 420
  },
  {
    "slug": "ancient-philosophy",
    "name": "Ancient Philosophy",
    "domain": "Philosophy & Psychology",
    "sort_order": 421
  },
  {
    "slug": "ethics",
    "name": "Ethics",
    "domain": "Philosophy & Psychology",
    "sort_order": 422
  },
  {
    "slug": "logic-and-reasoning",
    "name": "Logic & Reasoning",
    "domain": "Philosophy & Psychology",
    "sort_order": 423
  },
  {
    "slug": "existentialism",
    "name": "Existentialism",
    "domain": "Philosophy & Psychology",
    "sort_order": 424
  },
  {
    "slug": "famous-philosophers",
    "name": "Famous Philosophers",
    "domain": "Philosophy & Psychology",
    "sort_order": 425
  },
  {
    "slug": "cognitive-psychology",
    "name": "Cognitive Psychology",
    "domain": "Philosophy & Psychology",
    "sort_order": 426
  },
  {
    "slug": "freud-and-psychoanalysis",
    "name": "Freud & Psychoanalysis",
    "domain": "Philosophy & Psychology",
    "sort_order": 427
  },
  {
    "slug": "metaphysics",
    "name": "Metaphysics",
    "domain": "Philosophy & Psychology",
    "sort_order": 428
  },
  {
    "slug": "political-philosophy",
    "name": "Political Philosophy",
    "domain": "Philosophy & Psychology",
    "sort_order": 429
  },
  {
    "slug": "eastern-philosophy",
    "name": "Eastern Philosophy",
    "domain": "Philosophy & Psychology",
    "sort_order": 430
  },
  {
    "slug": "behavioral-psychology",
    "name": "Behavioral Psychology",
    "domain": "Philosophy & Psychology",
    "sort_order": 431
  },
  {
    "slug": "consciousness",
    "name": "Consciousness",
    "domain": "Philosophy & Psychology",
    "sort_order": 432
  },
  {
    "slug": "epistemology",
    "name": "Epistemology",
    "domain": "Philosophy & Psychology",
    "sort_order": 433
  },
  {
    "slug": "moral-dilemmas",
    "name": "Moral Dilemmas",
    "domain": "Philosophy & Psychology",
    "sort_order": 434
  },
  {
    "slug": "stoicism",
    "name": "Stoicism",
    "domain": "Philosophy & Psychology",
    "sort_order": 435
  },
  {
    "slug": "social-psychology",
    "name": "Social Psychology",
    "domain": "Philosophy & Psychology",
    "sort_order": 436
  },
  {
    "slug": "philosophy-of-mind",
    "name": "Philosophy of Mind",
    "domain": "Philosophy & Psychology",
    "sort_order": 437
  },
  {
    "slug": "personality-theory",
    "name": "Personality Theory",
    "domain": "Philosophy & Psychology",
    "sort_order": 438
  },
  {
    "slug": "memory-and-learning",
    "name": "Memory & Learning",
    "domain": "Philosophy & Psychology",
    "sort_order": 439
  },
  {
    "slug": "thought-experiments",
    "name": "Thought Experiments",
    "domain": "Philosophy & Psychology",
    "sort_order": 440
  },
  {
    "slug": "automobiles",
    "name": "Automobiles",
    "domain": "Transportation",
    "sort_order": 441
  },
  {
    "slug": "aviation",
    "name": "Aviation",
    "domain": "Transportation",
    "sort_order": 442
  },
  {
    "slug": "trains-and-railways",
    "name": "Trains & Railways",
    "domain": "Transportation",
    "sort_order": 443
  },
  {
    "slug": "ships-and-boats",
    "name": "Ships & Boats",
    "domain": "Transportation",
    "sort_order": 444
  },
  {
    "slug": "motorcycles",
    "name": "Motorcycles",
    "domain": "Transportation",
    "sort_order": 445
  },
  {
    "slug": "motor-racing",
    "name": "Motor Racing",
    "domain": "Transportation",
    "sort_order": 446
  },
  {
    "slug": "space-travel",
    "name": "Space Travel",
    "domain": "Transportation",
    "sort_order": 447
  },
  {
    "slug": "public-transit",
    "name": "Public Transit",
    "domain": "Transportation",
    "sort_order": 448
  },
  {
    "slug": "classic-cars",
    "name": "Classic Cars",
    "domain": "Transportation",
    "sort_order": 449
  },
  {
    "slug": "aircraft-types",
    "name": "Aircraft Types",
    "domain": "Transportation",
    "sort_order": 450
  },
  {
    "slug": "bridges-and-tunnels",
    "name": "Bridges & Tunnels",
    "domain": "Transportation",
    "sort_order": 451
  },
  {
    "slug": "bicycles",
    "name": "Bicycles",
    "domain": "Transportation",
    "sort_order": 452
  },
  {
    "slug": "electric-vehicles",
    "name": "Electric Vehicles",
    "domain": "Transportation",
    "sort_order": 453
  },
  {
    "slug": "shipping-and-ports",
    "name": "Shipping & Ports",
    "domain": "Transportation",
    "sort_order": 454
  },
  {
    "slug": "car-manufacturers",
    "name": "Car Manufacturers",
    "domain": "Transportation",
    "sort_order": 455
  },
  {
    "slug": "the-history-of-flight",
    "name": "The History of Flight",
    "domain": "Transportation",
    "sort_order": 456
  },
  {
    "slug": "submarines",
    "name": "Submarines",
    "domain": "Transportation",
    "sort_order": 457
  },
  {
    "slug": "highways-and-roads",
    "name": "Highways & Roads",
    "domain": "Transportation",
    "sort_order": 458
  },
  {
    "slug": "famous-voyages",
    "name": "Famous Voyages",
    "domain": "Transportation",
    "sort_order": 459
  },
  {
    "slug": "engines-and-motors",
    "name": "Engines & Motors",
    "domain": "Transportation",
    "sort_order": 460
  },
  {
    "slug": "weather-and-meteorology",
    "name": "Weather & Meteorology",
    "domain": "Nature & Environment",
    "sort_order": 461
  },
  {
    "slug": "climate-change",
    "name": "Climate Change",
    "domain": "Nature & Environment",
    "sort_order": 462
  },
  {
    "slug": "natural-disasters",
    "name": "Natural Disasters",
    "domain": "Nature & Environment",
    "sort_order": 463
  },
  {
    "slug": "ecosystems",
    "name": "Ecosystems",
    "domain": "Nature & Environment",
    "sort_order": 464
  },
  {
    "slug": "renewable-energy",
    "name": "Renewable Energy",
    "domain": "Nature & Environment",
    "sort_order": 465
  },
  {
    "slug": "forests",
    "name": "Forests",
    "domain": "Nature & Environment",
    "sort_order": 466
  },
  {
    "slug": "coral-reefs",
    "name": "Coral Reefs",
    "domain": "Nature & Environment",
    "sort_order": 467
  },
  {
    "slug": "rivers-and-watersheds",
    "name": "Rivers & Watersheds",
    "domain": "Nature & Environment",
    "sort_order": 468
  },
  {
    "slug": "geology-and-rocks",
    "name": "Geology & Rocks",
    "domain": "Nature & Environment",
    "sort_order": 469
  },
  {
    "slug": "minerals-and-gems",
    "name": "Minerals & Gems",
    "domain": "Nature & Environment",
    "sort_order": 470
  },
  {
    "slug": "plants-and-botany",
    "name": "Plants & Botany",
    "domain": "Nature & Environment",
    "sort_order": 471
  },
  {
    "slug": "fungi",
    "name": "Fungi",
    "domain": "Nature & Environment",
    "sort_order": 472
  },
  {
    "slug": "biomes",
    "name": "Biomes",
    "domain": "Nature & Environment",
    "sort_order": 473
  },
  {
    "slug": "pollution",
    "name": "Pollution",
    "domain": "Nature & Environment",
    "sort_order": 474
  },
  {
    "slug": "conservation",
    "name": "Conservation",
    "domain": "Nature & Environment",
    "sort_order": 475
  },
  {
    "slug": "soil-and-agriculture",
    "name": "Soil & Agriculture",
    "domain": "Nature & Environment",
    "sort_order": 476
  },
  {
    "slug": "glaciers-and-ice",
    "name": "Glaciers & Ice",
    "domain": "Nature & Environment",
    "sort_order": 477
  },
  {
    "slug": "earthquakes",
    "name": "Earthquakes",
    "domain": "Nature & Environment",
    "sort_order": 478
  },
  {
    "slug": "the-water-cycle",
    "name": "The Water Cycle",
    "domain": "Nature & Environment",
    "sort_order": 479
  },
  {
    "slug": "sustainability",
    "name": "Sustainability",
    "domain": "Nature & Environment",
    "sort_order": 480
  },
  {
    "slug": "chess",
    "name": "Chess",
    "domain": "Games, Hobbies & Curiosities",
    "sort_order": 481
  },
  {
    "slug": "card-games",
    "name": "Card Games",
    "domain": "Games, Hobbies & Curiosities",
    "sort_order": 482
  },
  {
    "slug": "board-games",
    "name": "Board Games",
    "domain": "Games, Hobbies & Curiosities",
    "sort_order": 483
  },
  {
    "slug": "puzzles-and-riddles",
    "name": "Puzzles & Riddles",
    "domain": "Games, Hobbies & Curiosities",
    "sort_order": 484
  },
  {
    "slug": "playing-cards",
    "name": "Playing Cards",
    "domain": "Games, Hobbies & Curiosities",
    "sort_order": 485
  },
  {
    "slug": "gambling-and-casinos",
    "name": "Gambling & Casinos",
    "domain": "Games, Hobbies & Curiosities",
    "sort_order": 486
  },
  {
    "slug": "magic-and-illusions",
    "name": "Magic & Illusions",
    "domain": "Games, Hobbies & Curiosities",
    "sort_order": 487
  },
  {
    "slug": "collecting",
    "name": "Collecting",
    "domain": "Games, Hobbies & Curiosities",
    "sort_order": 488
  },
  {
    "slug": "origami",
    "name": "Origami",
    "domain": "Games, Hobbies & Curiosities",
    "sort_order": 489
  },
  {
    "slug": "knitting-and-crafts",
    "name": "Knitting & Crafts",
    "domain": "Games, Hobbies & Curiosities",
    "sort_order": 490
  },
  {
    "slug": "gardening",
    "name": "Gardening",
    "domain": "Games, Hobbies & Curiosities",
    "sort_order": 491
  },
  {
    "slug": "fishing",
    "name": "Fishing",
    "domain": "Games, Hobbies & Curiosities",
    "sort_order": 492
  },
  {
    "slug": "amateur-photography",
    "name": "Amateur Photography",
    "domain": "Games, Hobbies & Curiosities",
    "sort_order": 493
  },
  {
    "slug": "astrology-and-the-zodiac",
    "name": "Astrology & the Zodiac",
    "domain": "Games, Hobbies & Curiosities",
    "sort_order": 494
  },
  {
    "slug": "tarot-and-fortune-telling",
    "name": "Tarot & Fortune Telling",
    "domain": "Games, Hobbies & Curiosities",
    "sort_order": 495
  },
  {
    "slug": "comic-books",
    "name": "Comic Books",
    "domain": "Games, Hobbies & Curiosities",
    "sort_order": 496
  },
  {
    "slug": "quiz-and-trivia-history",
    "name": "Quiz & Trivia History",
    "domain": "Games, Hobbies & Curiosities",
    "sort_order": 497
  },
  {
    "slug": "toys-and-games-history",
    "name": "Toys & Games History",
    "domain": "Games, Hobbies & Curiosities",
    "sort_order": 498
  },
  {
    "slug": "tabletop-role-playing",
    "name": "Tabletop Role-Playing",
    "domain": "Games, Hobbies & Curiosities",
    "sort_order": 499
  },
  {
    "slug": "world-records",
    "name": "World Records",
    "domain": "Games, Hobbies & Curiosities",
    "sort_order": 500
  }
]
